touchable_component
