Metadata-Version: 2.1
Name: touchable-component
Version: 2.1.2
Summary: Dash Touchable Component
Author: s_matsumoto <s_matsumoto@thinkup-sol.co.jp>
License: MIT
Classifier: Framework :: Dash
License-File: LICENSE
